{
  "7": [
    {
      "x": "54.1",
      "y": "15",
      "title": "Animation",
      "icon": "./img/icons/video.svg",
      "link": "resources/Animations/Page_7.mp4",
      "type": "video",
      "size": "1024x720"
    },
    {
      "x": "0",
      "y": "42",
      "title": "Audio",
      "icon": "./img/icons/audio.svg",
      "link": "audio/logo-audio.mp3",
      "type": "audio"
    }
  ],
  "12": [
    {
      "x": "0",
      "y": "10",
      "title": "Interactivity",
      "icon": "./img/icons/interactivities.svg",
      "link": "resources/Interactivities/Page/index.html?page=Page_12",
      "type": "iframe",
      "size": "1024x720"
    }
  ],
  "13": [
    {
      "x": "72.1",
      "y": "7",
      "title": "Animation",
      "icon": "./img/icons/video.svg",
      "link": "resources/Animations/Page_13.mp4",
      "type": "video",
      "size": "1024x720"
    }
  ],
  "15": [
    {
      "x": "0",
      "y": "5",
      "title": "Interactivity",
      "icon": "./img/icons/interactivities.svg",
      "link": "resources/Interactivities/Page/index.html?page=Page_15",
      "type": "iframe",
      "size": "1024x720"
    },
    {
      "x": "0",
      "y": "28",
      "title": "Interactivity",
      "icon": "./img/icons/interactivities.svg",
      "link": "resources/Interactivities/Page/index.html?page=Page_15_1",
      "type": "iframe",
      "size": "1024x720"
    }
  ],
  "16": [
    {
      "x": "0",
      "y": "5",
      "title": "Animation",
      "icon": "./img/icons/video.svg",
      "link": "resources/Animations/Page_16.mp4",
      "type": "video",
      "size": "1024x720"
    },
    {
      "x": "0",
      "y": "25",
      "title": "Interactivity",
      "icon": "./img/icons/interactivities.svg",
      "link": "resources/Interactivities/Page/index.html?page=Page_16",
      "type": "iframe",
      "size": "1024x720"
    },
    {
      "x": "0",
      "y": "45",
      "title": "Interactivity",
      "icon": "./img/icons/interactivities.svg",
      "link": "resources/Interactivities/Page/index.html?page=Page_16_1",
      "type": "iframe",
      "size": "1024x720"
    },
    {
      "x": "0",
      "y": "60",
      "title": "Interactivity",
      "icon": "./img/icons/interactivities.svg",
      "link": "resources/Interactivities/Page/index.html?page=Page_16_2",
      "type": "iframe",
      "size": "1024x720"
    },
    {
      "x": "0",
      "y": "75",
      "title": "Interactivity",
      "icon": "./img/icons/interactivities.svg",
      "link": "resources/Interactivities/Page/index.html?page=Page_16_3",
      "type": "iframe",
      "size": "1024x720"
    }
  ]
}
